README.txt
bootstrap.py
buildout.cfg
setup.py
Products/__init__.py
Products.WatermarkImage.egg-info/PKG-INFO
Products.WatermarkImage.egg-info/SOURCES.txt
Products.WatermarkImage.egg-info/dependency_links.txt
Products.WatermarkImage.egg-info/entry_points.txt
Products.WatermarkImage.egg-info/namespace_packages.txt
Products.WatermarkImage.egg-info/not-zip-safe
Products.WatermarkImage.egg-info/requires.txt
Products.WatermarkImage.egg-info/top_level.txt
Products/WatermarkImage/CHANGES.txt
Products/WatermarkImage/COPYRIGHT.txt
Products/WatermarkImage/LICENSE.txt
Products/WatermarkImage/README.txt
Products/WatermarkImage/VERSION.txt
Products/WatermarkImage/__init__.py
Products/WatermarkImage/configure.zcml
Products/WatermarkImage/eventhandlers.py
Products/WatermarkImage/image.py
Products/WatermarkImage/interfaces.py
Products/WatermarkImage/permissions.py
Products/WatermarkImage/browser/__init__.py
Products/WatermarkImage/browser/configure.zcml
Products/WatermarkImage/browser/image.py
Products/WatermarkImage/browser/tests/__init__.py
Products/WatermarkImage/browser/tests/test_image.py
Products/WatermarkImage/browser/tests/test_image_ranges.py
Products/WatermarkImage/tests/__init__.py
Products/WatermarkImage/tests/test_image.py
Products/WatermarkImage/www/add.pt
Products/WatermarkImage/www/edit.dtml
Products/WatermarkImage/www/thumbnail.dtml
Products/WatermarkImage/www/watermarked.dtml
Products/WatermarkImage/www/watermarkimage.gif