Metadata-Version: 1.0
Name: Products.WatermarkImage
Version: 1.0
Summary: Zope 2 Image with thumbnail and watermarking support
Home-page: http://pypi.python.org/pypi/Products.WatermarkImage
Author: Jens Vagelpohl
Author-email: jens@dataflake.org
License: ZPL 2.1 (http://www.zope.org/Resources/License/ZPL-2.1)
Keywords: web zope zope2 image
Platform: UNKNOWN
Classifier: Development Status :: 5 - Production/Stable
Classifier: Framework :: Zope2
Classifier: Intended Audience :: Developers
Classifier: License :: OSI Approved :: Zope Public License
Classifier: Programming Language :: Python
Classifier: Topic :: Internet :: WWW/HTTP :: Dynamic Content
Classifier: Topic :: Multimedia :: Graphics :: Presentation
Classifier: Topic :: Software Development
Classifier: Topic :: Software Development :: Libraries :: Python Modules
